savemelord/__init__.py
savemelord/banditproblem.txt
savemelord/doubleQL.txt
savemelord/gridworld.txt
savemelord/help.txt
savemelord/montecarlo.txt
savemelord/policyiter_policyeval.txt
savemelord/reader.py
savemelord/sampleaverage.txt
savemelord/sarsavq.txt
savemelord/temporal.txt
savemelord/ucb_and_optimal_val.txt
savemelord/value_iteration_gridworld.txt
savemelord-0.1.6.dist-info/METADATA
savemelord-0.1.6.dist-info/WHEEL
savemelord-0.1.6.dist-info/top_level.txt
savemelord-0.1.6.dist-info/RECORD
