Metadata-Version: 2.1
Name: savemelord
Version: 0.1.6
Summary: My cool package
